{
  "indexes": [
    {
      "collectionGroup": "users",
      "queryScope": "COLLECTION",
      "fields": [
        { "fieldPath": "bloodType", "order": "ASCENDING" },
        { "fieldPath": "lastDonation", "order": "DESCENDING" }
      ]
    },
    {
      "collectionGroup": "users",
      "queryScope": "COLLECTION",
      "fields": [
        { "fieldPath": "role", "order": "ASCENDING" },
        { "fieldPath": "createdAt", "order": "DESCENDING" }
      ]
    },
    {
      "collectionGroup": "appointments",
      "queryScope": "COLLECTION",
      "fields": [
        { "fieldPath": "status", "order": "ASCENDING" },
        { "fieldPath": "donationDate", "order": "ASCENDING" }
      ]
    },
    {
      "collectionGroup": "appointments",
      "queryScope": "COLLECTION",
      "fields": [
        { "fieldPath": "donorId", "order": "ASCENDING" },
        { "fieldPath": "createdAt", "order": "DESCENDING" }
      ]
    },
    {
      "collectionGroup": "appointments",
      "queryScope": "COLLECTION",
      "fields": [
        { "fieldPath": "hospitalId", "order": "ASCENDING" },
        { "fieldPath": "createdAt", "order": "DESCENDING" }
      ]
    },
    {
      "collectionGroup": "donationRequests",
      "queryScope": "COLLECTION",
      "fields": [
        { "fieldPath": "createdBy", "order": "ASCENDING" },
        { "fieldPath": "createdAt", "order": "DESCENDING" }
      ]
    },
    {
      "collectionGroup": "donationRequests",
      "queryScope": "COLLECTION",
      "fields": [
        { "fieldPath": "bloodType", "order": "ASCENDING" },
        { "fieldPath": "createdAt", "order": "DESCENDING" }
      ]
    },
    {
      "collectionGroup": "donationRequests",
      "queryScope": "COLLECTION",
      "fields": [
        { "fieldPath": "status", "order": "ASCENDING" },
        { "fieldPath": "urgency", "order": "DESCENDING" },
        { "fieldPath": "createdAt", "order": "DESCENDING" }
      ]
    },
    {
      "collectionGroup": "bloodInventory",
      "queryScope": "COLLECTION",
      "fields": [
        { "fieldPath": "hospitalId", "order": "ASCENDING" },
        { "fieldPath": "bloodType", "order": "ASCENDING" }
      ]
    },
    {
      "collectionGroup": "donations",
      "queryScope": "COLLECTION",
      "fields": [
        { "fieldPath": "donorId", "order": "ASCENDING" },
        { "fieldPath": "contentHash", "order": "ASCENDING" },
        { "fieldPath": "createdAt", "order": "ASCENDING" }
      ]
    },
    {
      "collectionGroup": "notifications",
      "queryScope": "COLLECTION",
      "fields": [
        { "fieldPath": "userId", "order": "ASCENDING" },
        { "fieldPath": "createdAt", "order": "DESCENDING" }
      ]
    },
    {
      "collectionGroup": "requests",
      "queryScope": "COLLECTION",
      "fields": [
        { "fieldPath": "userId", "order": "ASCENDING" },
        { "fieldPath": "createdAt", "order": "DESCENDING" }
      ]
    }
  ],
  "fieldOverrides": [
    {
      "collectionGroup": "donations",
      "fieldPath": "status",
      "indexes": [
        { "order": "ASCENDING", "queryScope": "COLLECTION" }
      ]
    },
    {
      "collectionGroup": "donations",
      "fieldPath": "donorId",
      "indexes": [
        { "order": "ASCENDING", "queryScope": "COLLECTION" }
      ]
    }
  ]
}
